x_pg_channels/__init__.py
x_pg_channels-0.0.1.dist-info/LICENSE
x_pg_channels-0.0.1.dist-info/METADATA
x_pg_channels-0.0.1.dist-info/WHEEL
x_pg_channels-0.0.1.dist-info/top_level.txt
x_pg_channels-0.0.1.dist-info/RECORD
