Metadata-Version: 2.1
Name: x_pg_channels
Version: 0.0.1
Summary: Generates PL/pgSQL script creating LISTEN/NOTIFY channels
Author-email: Mike Artemiev <mixartemev@gmail.com>
License: MIT
Project-URL: Homepage, https://github.com/mixartemev/pg-channels
Project-URL: Repository, https://github.com/mixartemev/pg-channels
Requires-Python: >=3.11
License-File: LICENSE
Provides-Extra: dev
Requires-Dist: pytest ; extra == 'dev'
Requires-Dist: build ; extra == 'dev'
Requires-Dist: twine ; extra == 'dev'
Requires-Dist: setuptools-scm ; extra == 'dev'
